Metadata-Version: 1.1
Name: every-script-is-a-vk-bot
Version: 1.3
Summary: This library can turn your code into the VK bot.
Home-page: https://github.com/megahomyak/every_script_is_a_vk_bot
Author: megahomyak
Author-email: g.megahomyak@gmail.com
License: OSI Approved :: GNU General Public License v3 (GPLv3)
Download-URL: https://github.com/megahomyak/every_script_is_a_vk_bot/archive/v1.3.tar.gz
Platform: UNKNOWN
